MANIFEST.in
README.md
setup.py
test/tester.py
uvsc/UVSC64.dll
uvsc/__init__.py
uvsc/uvsockwin.py
uvsc.egg-info/PKG-INFO
uvsc.egg-info/SOURCES.txt
uvsc.egg-info/dependency_links.txt
uvsc.egg-info/not-zip-safe
uvsc.egg-info/top_level.txt